pystributed/__init__.py
pystributed/config.py
pystributed/docker_utils.py
pystributed/main.py
pystributed/remote_utils.py
pystributed/save_for_remote_magic.py
pystributed-0.2.0.dist-info/METADATA
pystributed-0.2.0.dist-info/WHEEL
pystributed-0.2.0.dist-info/top_level.txt
pystributed-0.2.0.dist-info/RECORD
