Metadata-Version: 2.1
Name: pystributed
Version: 0.2.0
Summary: A utility to run Jupyter Notebook code on a remote server using Docker.
Home-page: https://github.com/eanthony76/pystributed
Author: Evan Anthony
Author-email: anthonyevanm@gmail.com
